odoo/addons/sale_disable_inventory_check/README.rst
odoo/addons/sale_disable_inventory_check/__init__.py
odoo/addons/sale_disable_inventory_check/__manifest__.py
odoo/addons/sale_disable_inventory_check/data/product_check_stock_data.xml
odoo/addons/sale_disable_inventory_check/i18n/de.po
odoo/addons/sale_disable_inventory_check/i18n/sale_disable_inventory_check.pot
odoo/addons/sale_disable_inventory_check/models/__init__.py
odoo/addons/sale_disable_inventory_check/models/product_category.py
odoo/addons/sale_disable_inventory_check/models/product_template.py
odoo/addons/sale_disable_inventory_check/models/sale_order_line.py
odoo/addons/sale_disable_inventory_check/static/description/icon.png
odoo/addons/sale_disable_inventory_check/tests/__init__.py
odoo/addons/sale_disable_inventory_check/tests/test_disable_inventory_check.py
odoo/addons/sale_disable_inventory_check/views/product_category_views.xml
odoo/addons/sale_disable_inventory_check/views/product_template_views.xml
odoo11_addon_sale_disable_inventory_check-11.0.2.0.0.dist-info/METADATA
odoo11_addon_sale_disable_inventory_check-11.0.2.0.0.dist-info/WHEEL
odoo11_addon_sale_disable_inventory_check-11.0.2.0.0.dist-info/top_level.txt
odoo11_addon_sale_disable_inventory_check-11.0.2.0.0.dist-info/RECORD
